{"function":"jme_centiseconds_normalize","engine":"VSOP_ELP_MEEUS","fixture_id":"modern_bhuj_standard","category":"engine_invariant","status":"OK","return_value":{"type":"int32","signed_decimal":"100","unsigned_decimal":"100","hex":"0x00000064","raw_le_hex":"64000000"},"timing":{"clock":"CLOCK_MONOTONIC","start":{"sec":{"type":"uint64","unsigned_decimal":"34856","hex":"0x0000000000008828","raw_le_hex":"2888000000000000"},"nsec":{"type":"uint64","unsigned_decimal":"16708848","hex":"0x0000000000fef4f0","raw_le_hex":"f0f4fe0000000000"}},"end":{"sec":{"type":"uint64","unsigned_decimal":"34856","hex":"0x0000000000008828","raw_le_hex":"2888000000000000"},"nsec":{"type":"uint64","unsigned_decimal":"16770950","hex":"0x0000000000ffe786","raw_le_hex":"86e7ff0000000000"}},"elapsed_ns":{"type":"uint64","unsigned_decimal":"62102","hex":"0x000000000000f296","raw_le_hex":"96f2000000000000"},"elapsed_seconds_decimal_string":"0.000062102"}}
