{"function":"jme_jpl_timescale","engine":"VSOP_ELP_MEEUS","fixture_id":"modern_bhuj_standard","category":"engine_invariant","status":"OK","return_value":{"type":"int32","signed_decimal":"0","unsigned_decimal":"0","hex":"0x00000000","raw_le_hex":"00000000"},"timing":{"clock":"CLOCK_MONOTONIC","start":{"sec":{"type":"uint64","unsigned_decimal":"30132","hex":"0x00000000000075b4","raw_le_hex":"b475000000000000"},"nsec":{"type":"uint64","unsigned_decimal":"476557746","hex":"0x000000001c67b1b2","raw_le_hex":"b2b1671c00000000"}},"end":{"sec":{"type":"uint64","unsigned_decimal":"30132","hex":"0x00000000000075b4","raw_le_hex":"b475000000000000"},"nsec":{"type":"uint64","unsigned_decimal":"476616969","hex":"0x000000001c689909","raw_le_hex":"0999681c00000000"}},"elapsed_ns":{"type":"uint64","unsigned_decimal":"59223","hex":"0x000000000000e757","raw_le_hex":"57e7000000000000"},"elapsed_seconds_decimal_string":"0.000059223"}}
