{"function":"jme_ecliptic_to_equatorial","engine":"MOSHIER","fixture_id":"modern_bhuj_standard","category":"engine_invariant","status":"OK","values":{"type":"double_array","length":{"type":"size_t","decimal_string":"2","raw_le_hex":"0200000000000000"},"elements":[{"index":"0","decimal_string":"0","hexfloat":"0x0p+0","raw_le_hex":"0000000000000000"},{"index":"1","decimal_string":"0","hexfloat":"0x0p+0","raw_le_hex":"0000000000000000"}],"raw_le_hex":"00000000000000000000000000000000"},"timing":{"clock":"CLOCK_MONOTONIC","start":{"sec":{"type":"uint64","unsigned_decimal":"869","hex":"0x0000000000000365","raw_le_hex":"6503000000000000"},"nsec":{"type":"uint64","unsigned_decimal":"967174044","hex":"0x0000000039a5e79c","raw_le_hex":"9ce7a53900000000"}},"end":{"sec":{"type":"uint64","unsigned_decimal":"869","hex":"0x0000000000000365","raw_le_hex":"6503000000000000"},"nsec":{"type":"uint64","unsigned_decimal":"967283491","hex":"0x0000000039a79323","raw_le_hex":"2393a73900000000"}},"elapsed_ns":{"type":"uint64","unsigned_decimal":"109447","hex":"0x000000000001ab87","raw_le_hex":"87ab010000000000"},"elapsed_seconds_decimal_string":"0.000109447"}}
