{"function":"jme_spherical_angular_separation","engine":"JPL","fixture_id":"modern_bhuj_standard","category":"engine_invariant","status":"OK","return_value":{"type":"double","decimal_string":"90","hexfloat":"0x1.68p+6","raw_le_hex":"0000000000805640"},"timing":{"clock":"CLOCK_MONOTONIC","start":{"sec":{"type":"uint64","unsigned_decimal":"912","hex":"0x0000000000000390","raw_le_hex":"9003000000000000"},"nsec":{"type":"uint64","unsigned_decimal":"705720482","hex":"0x000000002a1070a2","raw_le_hex":"a270102a00000000"}},"end":{"sec":{"type":"uint64","unsigned_decimal":"912","hex":"0x0000000000000390","raw_le_hex":"9003000000000000"},"nsec":{"type":"uint64","unsigned_decimal":"705753298","hex":"0x000000002a10f0d2","raw_le_hex":"d2f0102a00000000"}},"elapsed_ns":{"type":"uint64","unsigned_decimal":"32816","hex":"0x0000000000008030","raw_le_hex":"3080000000000000"},"elapsed_seconds_decimal_string":"0.000032816"}}
