{"function":"jme_centiseconds_difference","engine":"MOSHIER","fixture_id":"modern_bhuj_standard","category":"engine_invariant","status":"OK","return_value":{"type":"int32","signed_decimal":"100","unsigned_decimal":"100","hex":"0x00000064","raw_le_hex":"64000000"},"timing":{"clock":"CLOCK_MONOTONIC","start":{"sec":{"type":"uint64","unsigned_decimal":"22752","hex":"0x00000000000058e0","raw_le_hex":"e058000000000000"},"nsec":{"type":"uint64","unsigned_decimal":"504801305","hex":"0x000000001e16a819","raw_le_hex":"19a8161e00000000"}},"end":{"sec":{"type":"uint64","unsigned_decimal":"22752","hex":"0x00000000000058e0","raw_le_hex":"e058000000000000"},"nsec":{"type":"uint64","unsigned_decimal":"504839685","hex":"0x000000001e173e05","raw_le_hex":"053e171e00000000"}},"elapsed_ns":{"type":"uint64","unsigned_decimal":"38380","hex":"0x00000000000095ec","raw_le_hex":"ec95000000000000"},"elapsed_seconds_decimal_string":"0.000038380"}}
